.coveragerc
.travis.yml
AUTHORS.rst
CHANGES.rst
LICENSE.txt
README.rst
requirements.txt
setup.cfg
setup.py
test-requirements.txt
docs/Makefile
docs/authors.rst
docs/changes.rst
docs/conf.py
docs/index.rst
docs/license.rst
docs/_static/.gitignore
pymltk/__init__.py
pymltk/preprocessing.py
pymltk/utils.py
pymltk.egg-info/PKG-INFO
pymltk.egg-info/SOURCES.txt
pymltk.egg-info/dependency_links.txt
pymltk.egg-info/not-zip-safe
pymltk.egg-info/requires.txt
pymltk.egg-info/top_level.txt
tests/conftest.py
tests/test_preprocessing.py
tests/test_utils.py