Metadata-Version: 1.1
Name: pymltk
Version: 0.1
Summary: Python Machine Learning Toolkit
Home-page: https://github.com/bkomboz/pymltk
Author: Basil Komboz
Author-email: basil.komboz@gmx.de
License: new Apache
Platform: UNKNOWN
Classifier: Development Status :: 4 - Beta
Classifier: Programming Language :: Python
Classifier: Natural Language :: English
